intellikit/__init__.py
intellikit/common.py
intellikit/intellikit.py
intellikit/ir.py
intellikit/sim.py
intellikit-0.0.8.dist-info/LICENSE
intellikit-0.0.8.dist-info/METADATA
intellikit-0.0.8.dist-info/WHEEL
intellikit-0.0.8.dist-info/entry_points.txt
intellikit-0.0.8.dist-info/top_level.txt
intellikit-0.0.8.dist-info/RECORD
