Metadata-Version: 2.1
Name: intellikit
Version: 0.0.8
Summary: A python toolkit for case based reasoning, information retrieval, natural language processing and other techniques for AI and intelligent systems.
Author-email: Arthur Kakande <kaksarthur@gmail.com>
License: MIT License
Project-URL: Homepage, https://github.com/ArthurKakande/intellikit
Keywords: intellikit
Classifier: Intended Audience :: Developers
Classifier: License :: OSI Approved :: MIT License
Classifier: Natural Language :: English
Classifier: Programming Language :: Python :: 3.8
Classifier: Programming Language :: Python :: 3.9
Classifier: Programming Language :: Python :: 3.10
Classifier: Programming Language :: Python :: 3.11
Classifier: Programming Language :: Python :: 3.12
Requires-Python: >=3.8
License-File: LICENSE
Requires-Dist: numpy
Requires-Dist: pandas
Requires-Dist: scikit-learn
Requires-Dist: levenshtein
Requires-Dist: sentence-transformers
Requires-Dist: nltk
Requires-Dist: datasets
Requires-Dist: fsspec ==2024.10.0
Provides-Extra: all
Requires-Dist: intellikit[extra] ; extra == 'all'
Provides-Extra: extra
Requires-Dist: pandas ; extra == 'extra'
